<?xml version="1.0" encoding="UTF-8"?>
<files psalm-version="3.11.4@58e1d8e68e5098bf4fbfdfb420c38d563f882549">
  <file src="config/bootstrap.php">
    <MixedArgumentTypeCoercion occurrences="1">
      <code>$k</code>
    </MixedArgumentTypeCoercion>
    <MixedAssignment occurrences="6">
      <code>$env</code>
      <code>$v</code>
      <code>$_ENV[$k]</code>
      <code>$_ENV['APP_ENV']</code>
      <code>$_SERVER['APP_ENV']</code>
      <code>$_SERVER['APP_DEBUG']</code>
    </MixedAssignment>
  </file>
  <file src="src/Kernel.php">
    <MixedAssignment occurrences="2">
      <code>$contents</code>
      <code>$envs</code>
    </MixedAssignment>
    <MixedMethodCall occurrences="1">
      <code>new $class()</code>
    </MixedMethodCall>
    <UnresolvableInclude occurrences="1">
      <code>require $this-&gt;getProjectDir() . '/config/bundles.php'</code>
    </UnresolvableInclude>
  </file>
</files>
